gimagedownload/LICENSE
gimagedownload/README.MD
gimagedownload/__init__.py
gimagedownload/requirements.txt
gimagedownload/thirdparty.json
gimagedownload-0.10.dist-info/LICENSE.rst
gimagedownload-0.10.dist-info/METADATA
gimagedownload-0.10.dist-info/WHEEL
gimagedownload-0.10.dist-info/top_level.txt
gimagedownload-0.10.dist-info/RECORD
