Metadata-Version: 2.1
Name: gimagedownload
Version: 0.10
Summary: Download Google Image search results with free proxies
Home-page: https://github.com/hansalemaos/gimagedownload
Author: Johannes Fischer
Author-email: <aulasparticularesdealemaosp@gmail.com>
License: MIT
Keywords: download,scrape,site,google,images
Classifier: Development Status :: 4 - Beta
Classifier: Programming Language :: Python :: 3 :: Only
Classifier: Programming Language :: Python :: 3.9
Classifier: Topic :: Scientific/Engineering :: Visualization
Classifier: Topic :: Software Development :: Libraries :: Python Modules
Classifier: Topic :: Text Editors :: Text Processing
Classifier: Topic :: Text Processing :: General
Classifier: Topic :: Text Processing :: Indexing
Classifier: Topic :: Text Processing :: Filters
Classifier: Topic :: Utilities
License-File: LICENSE.rst
Requires-Dist: a-pandas-ex-apply-ignore-exceptions
Requires-Dist: get-consecutive-filename
Requires-Dist: list-all-files-recursively
Requires-Dist: pandas
Requires-Dist: Pillow
Requires-Dist: requests
Requires-Dist: site2hdd
Requires-Dist: tolerant-isinstance
Requires-Dist: url-analyzer
